pytorch_msssim/__init__.py
pytorch_msssim/ssim.py
pytorch_msssim-1.0.0.dist-info/LICENSE
pytorch_msssim-1.0.0.dist-info/METADATA
pytorch_msssim-1.0.0.dist-info/WHEEL
pytorch_msssim-1.0.0.dist-info/top_level.txt
pytorch_msssim-1.0.0.dist-info/RECORD
