Metadata-Version: 2.1
Name: pytorch-msssim
Version: 1.0.0
Summary: Fast and differentiable MS-SSIM and SSIM for pytorch.
Home-page: https://github.com/VainF/pytorch-msssim
Author: Gongfan Fang
Author-email: gongfan@u.nus.edu
Classifier: Programming Language :: Python :: 3
Classifier: License :: OSI Approved :: MIT License
Classifier: Operating System :: OS Independent
License-File: LICENSE
